note_taker_mcp/__init__.py
note_taker_mcp/index.py
note_taker_mcp/server.py
note_taker_mcp/storage.py
note_taker_mcp/tests/test_index.py
note_taker_mcp/tests/test_server.py
note_taker_mcp/tests/test_storage.py
note_taker_mcp-0.1.3.dist-info/METADATA
note_taker_mcp-0.1.3.dist-info/WHEEL
note_taker_mcp-0.1.3.dist-info/entry_points.txt
note_taker_mcp-0.1.3.dist-info/RECORD
