Metadata-Version: 2.4
Name: note-taker-mcp
Version: 0.1.3
Summary: MCP allowing short text notes to be persisted and retrieved locally for aiding in long context reasoning tasks
Project-URL: Repository, https://github.com/chriskyle/note-taker-mcp
Author: chriskyle, codex
Requires-Python: >=3.10
Requires-Dist: chromadb
Requires-Dist: fastmcp
